vmhub3/__init__.py
vmhub3/vmhub3.py
vmhub3-1.0.2.dist-info/LICENSE
vmhub3-1.0.2.dist-info/METADATA
vmhub3-1.0.2.dist-info/WHEEL
vmhub3-1.0.2.dist-info/entry_points.txt
vmhub3-1.0.2.dist-info/top_level.txt
vmhub3-1.0.2.dist-info/RECORD
