Metadata-Version: 2.1
Name: vmhub3
Version: 1.0.2
Summary: python module to send instructions to Virgin Media Hub 3.0 / Compal routers
Home-page: https://github.com/rpcsp/vmhub3
Author: rpcsp
Author-email: pcunha@hotmail.com
License: https://github.com/rpcsp/vmhub3/blob/main/LICENSE
Project-URL: Project page, https://github.com/rpcsp/vmhub3
Platform: UNKNOWN
Classifier: License :: OSI Approved :: MIT License
Classifier: Operating System :: OS Independent
Classifier: Programming Language :: Python :: 3
Classifier: Programming Language :: Python :: 3.6
Classifier: Programming Language :: Python :: 3.7
Classifier: Programming Language :: Python :: 3.8
Classifier: Programming Language :: Python :: 3.9
Classifier: Programming Language :: Python :: 3.10
Requires-Python: >=3.6
License-File: LICENSE
Requires-Dist: requests
Requires-Dist: xmltodict
